langchat/__init__.py
langchat/sdk.py
langchat/adapters/base.py
langchat/adapters/database/__init__.py
langchat/adapters/database/id_manager.py
langchat/adapters/database/supabase_adapter.py
langchat/adapters/database/supabase_provider.py
langchat/adapters/llm/__init__.py
langchat/adapters/llm/_base_llm.py
langchat/adapters/llm/anthropic_provider.py
langchat/adapters/llm/cohere_provider.py
langchat/adapters/llm/gemini_provider.py
langchat/adapters/llm/mistral_provider.py
langchat/adapters/llm/ollama_provider.py
langchat/adapters/llm/openai_provider.py
langchat/adapters/logger/__init__.py
langchat/adapters/reranker/__init__.py
langchat/adapters/reranker/flashrank_adapter.py
langchat/adapters/reranker/flashrank_provider.py
langchat/adapters/vector_db/__init__.py
langchat/adapters/vector_db/pinecone_adapter.py
langchat/adapters/vector_db/pinecone_provider.py
langchat/api/app.py
langchat/api/models.py
langchat/api/routes.py
langchat/core/engine.py
langchat/core/prompts.py
langchat/core/session.py
langchat/core/exceptions/__init__.py
langchat/core/utils/docker_generator.py
langchat/core/utils/document_indexer.py
langchat/core/utils/exceptions.py
langchat-1.0.1.dist-info/licenses/LICENSE
langchat-1.0.1.dist-info/METADATA
langchat-1.0.1.dist-info/WHEEL
langchat-1.0.1.dist-info/top_level.txt
langchat-1.0.1.dist-info/RECORD
