Metadata-Version: 2.4
Name: langchat
Version: 1.0.1
Summary: A powerful library for Ship production-grade AI chatbots in minutes
Home-page: https://github.com/neurobrains/langchat
Author: Sifat Hasan, NeuroBrain
Author-email: contact@neurobrains.co
License: MIT
Keywords: rag,llm,ai,langchain,chatbot,vector-search,retrieval-augmented-generation
Classifier: Development Status :: 4 - Beta
Classifier: Intended Audience :: Developers
Classifier: Topic :: Software Development :: Libraries :: Python Modules
Classifier: Topic :: Scientific/Engineering :: Artificial Intelligence
Classifier: Programming Language :: Python :: 3
Classifier: Programming Language :: Python :: 3.8
Classifier: Programming Language :: Python :: 3.9
Classifier: Programming Language :: Python :: 3.10
Classifier: Programming Language :: Python :: 3.11
Classifier: License :: OSI Approved :: MIT License
Classifier: Operating System :: OS Independent
Requires-Python: >=3.8
License-File: LICENSE
Requires-Dist: fastapi>=0.115.14
Requires-Dist: uvicorn>=0.34.3
Requires-Dist: starlette>=0.46.2
Requires-Dist: pydantic>=2.11.7
Requires-Dist: python-multipart>=0.0.20
Requires-Dist: pytz>=2022.7
Requires-Dist: requests>=2.32.3
Requires-Dist: langchain==0.3.27
Requires-Dist: langchain-core<1.0.0,>=0.3.72
Requires-Dist: langchain-pinecone<0.3.0,>=0.1.0
Requires-Dist: langchain-community<0.4.0,>=0.3.0
Requires-Dist: langchain-openai<0.3.0,>=0.2.0
Requires-Dist: openai
Requires-Dist: tiktoken>=0.9.0
Requires-Dist: pinecone-client
Requires-Dist: flashrank>=0.2.10
Requires-Dist: supabase>=2.15.2
Requires-Dist: docsuite>=0.1.0
Requires-Dist: pyperclip>=1.11.0
Provides-Extra: dev
Requires-Dist: pytest>=7.0.0; extra == "dev"
Requires-Dist: pytest-asyncio>=0.21.0; extra == "dev"
Requires-Dist: black>=23.0.0; extra == "dev"
Requires-Dist: flake8>=6.0.0; extra == "dev"
Requires-Dist: ty>=0.0.1; extra == "dev"
Requires-Dist: ruff>=0.1.0; extra == "dev"
Dynamic: author-email
Dynamic: home-page
Dynamic: license-file
Dynamic: requires-python
